smartdata/__init__.py
smartdata/config.py
smartdata/custom_agent.py
smartdata/memory.py
smartdata/modeler.py
smartdata/util.py
smartdataai-1.2.dist-info/METADATA
smartdataai-1.2.dist-info/WHEEL
smartdataai-1.2.dist-info/top_level.txt
smartdataai-1.2.dist-info/RECORD
