Metadata-Version: 2.1
Name: smartdataai
Version: 1.2
Summary: SmartDataAI: Intelligent Data Cleaning, Transformation, Charting, and Analysis with LLM
Home-page: https://github.com/talentai/SmartDataAI
Author: TalentAINow
Author-email: contact@talentainow.com
Classifier: Programming Language :: Python :: 3
Classifier: License :: OSI Approved :: MIT License
Classifier: Operating System :: OS Independent
Requires-Python: >=3.6
Requires-Dist: pandas
Requires-Dist: numpy
Requires-Dist: matplotlib
Requires-Dist: seaborn
Requires-Dist: statsmodels
Requires-Dist: scipy
Requires-Dist: scikit-learn
Requires-Dist: langchain
Requires-Dist: langchain-community
Requires-Dist: langchain-core
Requires-Dist: langchain-experimental
Requires-Dist: langchain-openai
